LICENSE
MANIFEST.in
README.md
pyproject.toml
setup.py
aws_cdk_cli/__init__.py
aws_cdk_cli/__main__.py
aws_cdk_cli/cli.py
aws_cdk_cli/constants.py
aws_cdk_cli/download.py
aws_cdk_cli/installer.py
aws_cdk_cli/post_install.py
aws_cdk_cli/runtime.py
aws_cdk_cli/semver_helper.py
aws_cdk_cli/version.py
aws_cdk_cli.egg-info/PKG-INFO
aws_cdk_cli.egg-info/SOURCES.txt
aws_cdk_cli.egg-info/dependency_links.txt
aws_cdk_cli.egg-info/entry_points.txt
aws_cdk_cli.egg-info/requires.txt
aws_cdk_cli.egg-info/top_level.txt
aws_cdk_cli/node_modules/aws-cdk/LICENSE
aws_cdk_cli/node_modules/aws-cdk/NOTICE
aws_cdk_cli/node_modules/aws-cdk/README.md
aws_cdk_cli/node_modules/aws-cdk/THIRD_PARTY_LICENSES
aws_cdk_cli/node_modules/aws-cdk/build-info.json
aws_cdk_cli/node_modules/aws-cdk/db.json.gz
aws_cdk_cli/node_modules/aws-cdk/metadata.json
aws_cdk_cli/node_modules/aws-cdk/package.json
aws_cdk_cli/node_modules/aws-cdk/release.txt
aws_cdk_cli/node_modules/aws-cdk/bin/cdk
aws_cdk_cli/node_modules/aws-cdk/docs/deploy-architecture.md
aws_cdk_cli/node_modules/aws-cdk/lib/api-private.d.ts
aws_cdk_cli/node_modules/aws-cdk/lib/api-private.js
aws_cdk_cli/node_modules/aws-cdk/lib/context-providers.d.ts
aws_cdk_cli/node_modules/aws-cdk/lib/context-providers.js
aws_cdk_cli/node_modules/aws-cdk/lib/index.d.ts
aws_cdk_cli/node_modules/aws-cdk/lib/index.js
aws_cdk_cli/node_modules/aws-cdk/lib/index_bg.wasm
aws_cdk_cli/node_modules/aws-cdk/lib/legacy-exports.d.ts
aws_cdk_cli/node_modules/aws-cdk/lib/legacy-exports.js
aws_cdk_cli/node_modules/aws-cdk/lib/util.d.ts
aws_cdk_cli/node_modules/aws-cdk/lib/util.js
aws_cdk_cli/node_modules/aws-cdk/lib/api/aws-auth.d.ts
aws_cdk_cli/node_modules/aws-cdk/lib/api/aws-auth.js
aws_cdk_cli/node_modules/aws-cdk/lib/api/bootstrap.d.ts
aws_cdk_cli/node_modules/aws-cdk/lib/api/bootstrap.js
aws_cdk_cli/node_modules/aws-cdk/lib/api/cloud-assembly.d.ts
aws_cdk_cli/node_modules/aws-cdk/lib/api/cloud-assembly.js
aws_cdk_cli/node_modules/aws-cdk/lib/api/cloudformation.d.ts
aws_cdk_cli/node_modules/aws-cdk/lib/api/cloudformation.js
aws_cdk_cli/node_modules/aws-cdk/lib/api/context.d.ts
aws_cdk_cli/node_modules/aws-cdk/lib/api/context.js
