Metadata-Version: 2.4
Name: aws-cdk-cli
Version: 2.1101.0
Summary: Python wrapper for AWS CDK CLI with smart Node.js runtime management
Home-page: https://github.com/rvben/aws-cdk-cli-py
Author-email: "Ruben J. Jongejan" <ruben.jongejan@gmail.com>
License: MIT
Classifier: Development Status :: 3 - Alpha
Classifier: Intended Audience :: Developers
Classifier: License :: OSI Approved :: MIT License
Classifier: Programming Language :: Python :: 3
Classifier: Programming Language :: Python :: 3.10
Classifier: Programming Language :: Python :: 3.11
Classifier: Programming Language :: Python :: 3.12
Classifier: Programming Language :: Python :: 3.13
Requires-Python: >=3.7
License-File: LICENSE
Provides-Extra: dev
Requires-Dist: pytest>=8.0.0; extra == "dev"
Requires-Dist: ruff>=0.8.0; extra == "dev"
Provides-Extra: docs
Requires-Dist: sphinx<9,>=8.0.0; extra == "docs"
Requires-Dist: sphinx-rtd-theme>=3.0.0; extra == "docs"
Dynamic: home-page
Dynamic: license-file
Dynamic: requires-python
